usn/__init__.py
usn/tests/__init__.py
usn/tests/data/grub_expected.cfg
usn/tests/data/grub_ubuntu-20.04.2-live-server-arm64.cfg
usn/tests/test_grub_cfg.py
usn/ubuntu_server_netboot.py
usn/usn.py
ubuntu_server_netboot-0.1.1.dist-info/entry_points.txt
ubuntu_server_netboot-0.1.1.dist-info/LICENSE
ubuntu_server_netboot-0.1.1.dist-info/WHEEL
ubuntu_server_netboot-0.1.1.dist-info/METADATA
ubuntu_server_netboot-0.1.1.dist-info/RECORD
