Metadata-Version: 2.1
Name: ubuntu-server-netboot
Version: 0.1.1
Summary: This utility generates a netboot directory tree from an Ubuntu Server Live ISO image, an image based on the subiquity installer.
License: GPL-2.0-only
Author: dann frazier
Author-email: dannf@ubuntu.com
Requires-Python: >=3.6.5,<4.0.0
Classifier: Development Status :: 6 - Mature
Classifier: Environment :: Console
Classifier: Intended Audience :: System Administrators
Classifier: License :: OSI Approved :: GNU General Public License v2 (GPLv2)
Classifier: Natural Language :: English
Classifier: Operating System :: POSIX
Classifier: Programming Language :: Python :: 3
Classifier: Programming Language :: Python :: 3 :: Only
Classifier: Programming Language :: Python :: 3.7
Classifier: Programming Language :: Python :: 3.8
Classifier: Programming Language :: Python :: 3.9
Classifier: Topic :: System :: Installation/Setup
Classifier: Topic :: Utilities
